accessgrid/__init__.py
accessgrid/client.py
accessgrid-0.1.6.dist-info/licenses/LICENSE
tests/__init__.py
tests/test_accessgrid.py
accessgrid-0.1.6.dist-info/METADATA
accessgrid-0.1.6.dist-info/WHEEL
accessgrid-0.1.6.dist-info/top_level.txt
accessgrid-0.1.6.dist-info/RECORD
